{"name":"函数参数传递","postlist":[{"title":"C++的lambda表达式使用方法","slug":"C++的lambda表达式使用方法","date":"2023-02-14T13:56:00.000Z","updated":"2023-11-26T09:07:01.080Z","comments":true,"path":"api/articles/C++的lambda表达式使用方法.json","excerpt":null,"keywords":null,"cover":null,"content":null,"raw":null,"categories":[{"name":"C++","path":"api/categories/C++.json"}],"tags":[{"name":"C++","path":"api/tags/C++.json"},{"name":"函数参数传递","path":"api/tags/函数参数传递.json"},{"name":"lambda表达式","path":"api/tags/lambda表达式.json"}]},{"title":"函数参数传递之引用与指针","slug":"函数参数传递之引用与指针","date":"2022-11-12T08:59:07.000Z","updated":"2023-11-26T09:07:01.080Z","comments":true,"path":"api/articles/函数参数传递之引用与指针.json","excerpt":null,"keywords":null,"cover":"https://cdn.jsdelivr.net/gh/geiyiren/MyBlogImage1/%E5%87%BD%E6%95%B0%E5%8F%82%E6%95%B0%E4%BC%A0%E9%80%92%E4%B9%8B%E5%BC%95%E7%94%A8%E4%B8%8E%E6%8C%87%E9%92%88/no.png","content":null,"raw":null,"categories":[{"name":"C++","path":"api/categories/C++.json"}],"tags":[{"name":"C++","path":"api/tags/C++.json"},{"name":"函数参数传递","path":"api/tags/函数参数传递.json"},{"name":"引用与指针","path":"api/tags/引用与指针.json"}]}]}